crafting/__init__.py
crafting/basic_config.yaml
crafting/config_validation.py
crafting/main.py
crafting/minecraft_names.json
crafting/utils.py
crafting-0.201.5.dist-info/METADATA
crafting-0.201.5.dist-info/WHEEL
crafting-0.201.5.dist-info/entry_points.txt
crafting-0.201.5.dist-info/top_level.txt
crafting-0.201.5.dist-info/RECORD
