Metadata-Version: 2.1
Name: crafting
Version: 0.201.5
Summary: Tool to run your DL/RL experiments with Docker
Home-page: https://github.com/Tviskaron/crafting
Author: Alexey Skrynnik
License: MIT
Requires-Python: >=3.6
Requires-Dist: PyYAML
Requires-Dist: docker
Requires-Dist: pydantic
